[
  {
    "model": "inventory.producttype",
    "pk": 1,
    "fields": {
      "name": "book"
    }
  },
  {
    "model": "inventory.producttype",
    "pk": 2,
    "fields": {
      "name": "incense"
    }
  },
  {
    "model": "inventory.producttype",
    "pk": 3,
    "fields": {
      "name": "mounted icon"
    }
  },
  {
    "model": "inventory.producttype",
    "pk": 4,
    "fields": {
      "name": "icon print"
    }
  },
  {
    "model": "inventory.productspecification",
    "pk": 1,
    "fields": {
      "product_type": 3,
      "name": "size"
    }
  },
  {
    "model": "inventory.productspecification",
    "pk": 2,
    "fields": {
      "product_type": 2,
      "name": "size"
    }
  },
  {
    "model": "inventory.productspecification",
    "pk": 3,
    "fields": {
      "product_type": 4,
      "name": "size"
    }
  },
  {
    "model": "inventory.productinventory",
    "pk": 1,
    "fields": {
      "product": 1,
      "product_type": 1,
      "sku": "b001",
      "restock_point": null,
      "target_amount": 10,
      "weight": "16.00",
      "price": "16.00"
    }
  },
  {
    "model": "inventory.productinventory",
    "pk": 2,
    "fields": {
      "product": 2,
      "product_type": 3,
      "sku": "a00100",
      "restock_point": 5,
      "target_amount": 10,
      "weight": "29.00",
      "price": "29.00"
    }
  },
  {
    "model": "inventory.productinventory",
    "pk": 3,
    "fields": {
      "product": 2,
      "product_type": 4,
      "sku": "a00101",
      "restock_point": 6,
      "target_amount": 10,
      "weight": "0.01",
      "price": "17.00"
    }
  },
  {
    "model": "inventory.productinventory",
    "pk": 4,
    "fields": {
      "product": 2,
      "product_type": 3,
      "sku": "a00110",
      "restock_point": 4,
      "target_amount": 10,
      "weight": "39.00",
      "price": "59.00"
    }
  },
  {
    "model": "inventory.productinventory",
    "pk": 5,
    "fields": {
      "product": 6,
      "product_type": 2,
      "sku": "in010",
      "restock_point": null,
      "target_amount": 10,
      "weight": "17.00",
      "price": "29.00"
    }
  },
  {
    "model": "inventory.productinventory",
    "pk": 6,
    "fields": {
      "product": 6,
      "product_type": 2,
      "sku": "in011",
      "restock_point": null,
      "target_amount": 10,
      "weight": "9.00",
      "price": "19.00"
    }
  },
  {
    "model": "inventory.productinventory",
    "pk": 7,
    "fields": {
      "product": 6,
      "product_type": 2,
      "sku": "in012",
      "restock_point": null,
      "target_amount": 10,
      "weight": "1.00",
      "price": "9.99"
    }
  },
  {
    "model": "inventory.productinventory",
    "pk": 8,
    "fields": {
      "product": 4,
      "product_type": 3,
      "sku": "a0211",
      "restock_point": 5,
      "target_amount": 10,
      "weight": "19.90",
      "price": "33.00"
    }
  },
  {
    "model": "inventory.productinventory",
    "pk": 9,
    "fields": {
      "product": 4,
      "product_type": 4,
      "sku": "a0222",
      "restock_point": 8,
      "target_amount": 11,
      "weight": "0.10",
      "price": "11.00"
    }
  },
  {
    "model": "inventory.productinventory",
    "pk": 10,
    "fields": {
      "product": 5,
      "product_type": 3,
      "sku": "a00333",
      "restock_point": 3,
      "target_amount": 12,
      "weight": "20.00",
      "price": "19.99"
    }
  },
  {
    "model": "inventory.productinventory",
    "pk": 11,
    "fields": {
      "product": 7,
      "product_type": 4,
      "sku": "a077",
      "restock_point": 2,
      "target_amount": 7,
      "weight": "0.01",
      "price": "9.89"
    }
  },
  {
    "model": "inventory.productinventory",
    "pk": 12,
    "fields": {
      "product": 3,
      "product_type": 4,
      "sku": "a00101.123x4",
      "restock_point": 1,
      "target_amount": 2,
      "weight": "0.10",
      "price": "11.90"
    }
  },
  {
    "model": "inventory.productspecificationvalue",
    "pk": 1,
    "fields": {
      "specification": 1,
      "sku": 2,
      "value": "8x10"
    }
  },
  {
    "model": "inventory.productspecificationvalue",
    "pk": 2,
    "fields": {
      "specification": 2,
      "sku": 7,
      "value": "ounce"
    }
  },
  {
    "model": "inventory.productspecificationvalue",
    "pk": 3,
    "fields": {
      "specification": 2,
      "sku": 6,
      "value": "half a pound"
    }
  },
  {
    "model": "inventory.productspecificationvalue",
    "pk": 4,
    "fields": {
      "specification": 2,
      "sku": 5,
      "value": "pound"
    }
  },
  {
    "model": "inventory.productspecificationvalue",
    "pk": 5,
    "fields": {
      "specification": 1,
      "sku": 8,
      "value": "8x10"
    }
  },
  {
    "model": "inventory.productspecificationvalue",
    "pk": 7,
    "fields": {
      "specification": 1,
      "sku": 4,
      "value": "16x24"
    }
  },
  {
    "model": "inventory.productspecificationvalue",
    "pk": 8,
    "fields": {
      "specification": 1,
      "sku": 10,
      "value": "8x10"
    }
  },
  {
    "model": "inventory.stock",
    "pk": 1,
    "fields": {
      "room": 1,
      "product": 2,
      "quantity": 0
    }
  },
  {
    "model": "inventory.stock",
    "pk": 3,
    "fields": {
      "room": 2,
      "product": 2,
      "quantity": 0
    }
  },
  {
    "model": "inventory.stock",
    "pk": 4,
    "fields": {
      "room": 3,
      "product": 2,
      "quantity": 1
    }
  },
  {
    "model": "inventory.stock",
    "pk": 5,
    "fields": {
      "room": 3,
      "product": 10,
      "quantity": 2
    }
  },
  {
    "model": "inventory.stock",
    "pk": 6,
    "fields": {
      "room": 4,
      "product": 2,
      "quantity": 3
    }
  },
  {
    "model": "inventory.stock",
    "pk": 9,
    "fields": {
      "room": 4,
      "product": 11,
      "quantity": 1
    }
  },
  {
    "model": "inventory.room",
    "pk": 1,
    "fields": {
      "name": "Sanding Room",
      "slug": "sanding"
    }
  },
  {
    "model": "inventory.room",
    "pk": 2,
    "fields": {
      "name": "Mounting Room",
      "slug": "mounting"
    }
  },
  {
    "model": "inventory.room",
    "pk": 3,
    "fields": {
      "name": "Painting Room",
      "slug": "painting"
    }
  },
  {
    "model": "inventory.room",
    "pk": 4,
    "fields": {
      "name": "Wrapping Room",
      "slug": "wrapping"
    }
  }
]
