[
  {
    "model": "inventory.producttype",
    "pk": 1,
    "fields": {
      "name": "book"
    }
  },
  {
    "model": "inventory.producttype",
    "pk": 2,
    "fields": {
      "name": "incense"
    }
  },
  {
    "model": "inventory.producttype",
    "pk": 3,
    "fields": {
      "name": "mounted icon"
    }
  },
  {
    "model": "inventory.producttype",
    "pk": 4,
    "fields": {
      "name": "icon print"
    }
  },
  {
    "model": "inventory.producttype",
    "pk": 5,
    "fields": {
      "name": "Metal Item"
    }
  }
]
